excalibur007001/__init__.py
excalibur007001/module.py
tests/__init__.py
tests/test_module.py
excalibur007001-0.0.2.dist-info/LICENSE
excalibur007001-0.0.2.dist-info/METADATA
excalibur007001-0.0.2.dist-info/WHEEL
excalibur007001-0.0.2.dist-info/top_level.txt
excalibur007001-0.0.2.dist-info/RECORD
