Metadata-Version: 2.1
Name: excalibur007001
Version: 0.0.2
Summary: Its just for the testing purpose
Home-page: UNKNOWN
Author: Dipanshu Kumar
Author-email: dipanshukumar449@gmail.com
License: UNKNOWN
Platform: UNKNOWN
Classifier: Programming Language :: Python :: 3
Classifier: License :: OSI Approved :: MIT License
Classifier: Operating System :: OS Independent
Requires-Python: >=3.6
License-File: LICENSE
